{
    "@class": "com.kony.gen.viz.model.component.KVizMap",
    "DNDConfig": null,
    "__parentReadjusting__": false,
    "_height_": {
        "type": "string",
        "value": "40%"
    },
    "_left_": {
        "type": "string",
        "value": "0%"
    },
    "_margin_": [
        0,
        0,
        0,
        0
    ],
    "_mode_": 1,
    "_padding_": [
        0,
        0,
        0,
        0
    ],
    "_top_": {
        "type": "string",
        "value": "0%"
    },
    "_width_": {
        "type": "string",
        "value": "100%"
    },
    "calloutwidth": 80,
    "canUpdateUI": true,
    "containerweight": 100,
    "defaultpinimage": "pinb.png",
    "id": "mapNearMe",
    "info": null,
    "invokedProperty": "maps",
    "iscustomlayout": false,
    "isvisible": true,
    "kuid": "da3722322d2d4f2187d10e7577cc2ee5",
    "locationdata": [],
    "mapsource": "non-native",
    "mapsrc": "non-native",
    "name": "kony.ui.Map",
    "parent": "frmOffersNear",
    "pf": "frmOffersNearMe",
    "provider": "google",
    "retaincontentalignment": false,
    "retainflexpositionproperties": false,
    "screenlevelwidget": false,
    "wType": "Map",
    "zoomlevel": 4
}